[
    {
        "Name": "BepInEx",
        "Version": "5.4.22",
        "Author": "BepInEx Team",
        "URI": "https://github.com/BepInEx/BepInEx/releases/download/v5.4.22/BepInEx_x64_5.4.22.0.zip",
        "Category":"Core"
    },
    {
        "Name": "More Company",
        "Version": "1.7.2",
        "Author": "notnotnotswipez",
        "URI": "https://thunderstore.io/package/download/notnotnotswipez/MoreCompany/1.7.2/",
        "Category":"Customization"
    },
    {
        "Name": "More Suites",
        "Version": "1.4.1",
        "Author": " x753",
        "URI": "https://thunderstore.io/package/download/x753/More_Suits/1.4.1/",
        "Category":"Customization"
    }
]
